{
    "id": 11598,
    "range": [
        121.816804,
        31.102716,
        121.826804,
        31.092716
    ],
    "image_path": "CitySatellite\\Shanghai\\11598.jpg",
    "poi": [],
    "places": [],
    "transport": [
        [
            5621,
            6,
            1
        ]
    ],
    "traffic": [],
    "buildings": [],
    "landuse": [
        [
            7201,
            2,
            4,
            0.115342
        ]
    ],
    "road_inner": [
        [
            5122,
            4,
            4,
            1044.3701666666668
        ],
        [
            5121,
            2,
            4,
            702.2893333333334
        ],
        [
            5112,
            1.0,
            1,
            1802.1278
        ],
        [
            5115,
            1.0,
            3,
            893.1931666666667
        ],
        [
            5141,
            1.0,
            5,
            729.27375
        ]
    ],
    "road_connect": {
        "11840": {
            "1": 1
        },
        "11720": {
            "1": 1
        },
        "11718": {
            "1": 2,
            "5": 1,
            "4": 1,
            "3": 1
        },
        "11719": {
            "1": 2,
            "4": 1
        },
        "11478": {
            "3": 2,
            "4": 7
        },
        "11479": {
            "4": 2
        },
        "11599": {
            "3": 1,
            "4": 3
        },
        "11596": {
            "5": 1
        },
        "11597": {
            "5": 1,
            "1": 2
        }
    },
    "population": [
        2150.671720504761
    ],
    "transport_embedding": [
        -0.8102989792823792,
        -1.608131766319275,
        -1.5528532266616821,
        0.5744320154190063,
        -2.2908363342285156,
        -0.6501294374465942,
        -2.264202117919922,
        1.8668322563171387,
        1.3163642883300781,
        -0.4517788589000702
    ],
    "roadnet_embedding": [
        0.5578091144561768,
        -0.9799681305885315,
        -0.5501388311386108,
        0.12056303769350052,
        0.673671305179596,
        -0.7777603268623352,
        -0.612405002117157,
        -0.9108757376670837,
        1.482265830039978,
        0.22881506383419037
    ],
    "function_embedding": [
        -0.5508159399032593,
        -0.38123610615730286,
        -0.13355796039104462,
        0.08246435225009918,
        -1.3705099821090698,
        0.0264345221221447,
        -0.04660455510020256,
        0.03634007275104523,
        0.018790701404213905,
        0.3740285038948059
    ],
    "city_embedding": [
        -0.9905387163162231,
        -0.011814509518444538,
        0.3860660791397095,
        1.0821781158447266,
        -0.6272921562194824,
        1.051186203956604,
        0.4956377148628235,
        3.0853066444396973,
        2.25974702835083,
        2.985396146774292
    ],
    "degree_embedding": [
        -1.0256686210632324,
        0.8916012644767761,
        0.23373255133628845,
        0.1574990600347519,
        -0.7496738433837891,
        -1.4416829347610474,
        -2.0021116733551025,
        -0.9141383767127991,
        -0.024618234485387802,
        -0.9075213074684143
    ]
}