{
    "id": 12702,
    "range": [
        121.906804,
        30.862716,
        121.916804,
        30.852716
    ],
    "image_path": "CitySatellite\\Shanghai\\12702.jpg",
    "poi": [],
    "places": [],
    "transport": [],
    "traffic": [],
    "buildings": [
        3,
        1460.155
    ],
    "landuse": [
        [
            7204,
            3,
            3,
            5.6443566190476195
        ],
        [
            7229,
            1,
            5,
            1.1204966666666667
        ]
    ],
    "road_inner": [
        [
            5122,
            2,
            4,
            1458.8308666666665
        ],
        [
            5141,
            7,
            5,
            2001.2851666666668
        ],
        [
            5121,
            1,
            4,
            251.802
        ],
        [
            5111,
            1.0,
            1,
            1938.8646601398602
        ],
        [
            5115,
            1.0,
            3,
            1146.1747083333332
        ],
        [
            5131,
            1.0,
            1,
            329.218
        ],
        [
            5142,
            1.0,
            5,
            414.04266666666666
        ]
    ],
    "road_connect": {
        "11862": {
            "4": 1
        },
        "11982": {
            "4": 1
        },
        "11983": {
            "4": 1
        },
        "12103": {
            "4": 1
        },
        "12223": {
            "4": 1
        },
        "12343": {
            "4": 1
        },
        "12463": {
            "4": 1
        },
        "12582": {
            "4": 1,
            "1": 3,
            "5": 2
        },
        "12583": {
            "4": 1
        },
        "12824": {
            "1": 2
        },
        "12825": {
            "1": 2
        },
        "12823": {
            "1": 2
        },
        "12946": {
            "1": 2
        },
        "12945": {
            "1": 2
        },
        "13066": {
            "1": 2
        },
        "13067": {
            "1": 2
        },
        "13068": {
            "1": 2
        },
        "13188": {
            "1": 2
        },
        "12581": {
            "1": 3,
            "5": 3
        },
        "12703": {
            "1": 2
        },
        "12822": {
            "3": 1,
            "4": 1
        },
        "12821": {
            "3": 2,
            "4": 1
        },
        "12941": {
            "3": 1
        },
        "13180": {
            "3": 1
        },
        "13181": {
            "3": 1
        },
        "13061": {
            "3": 1
        },
        "13300": {
            "3": 1
        },
        "12701": {
            "3": 2,
            "5": 3,
            "4": 2
        },
        "12460": {
            "1": 1
        },
        "12461": {
            "1": 1
        }
    },
    "population": [
        37.4646738931763
    ],
    "transport_embedding": [
        -0.1982385814189911,
        -0.6832229495048523,
        0.5643643140792847,
        -0.7459341287612915,
        0.5978049039840698,
        0.5219016075134277,
        -0.09327199310064316,
        1.2817972898483276,
        -0.9564770460128784,
        -0.43772092461586
    ],
    "roadnet_embedding": [
        0.6926422119140625,
        -1.0114047527313232,
        -0.9085425734519958,
        0.3468715250492096,
        0.4534881114959717,
        0.6803566217422485,
        -0.2828570604324341,
        -1.167911410331726,
        0.7721939086914062,
        -0.20530574023723602
    ],
    "function_embedding": [
        -1.5760329961776733,
        -0.07530813664197922,
        2.0022318363189697,
        0.44677892327308655,
        0.6200135350227356,
        2.527146577835083,
        -0.295527845621109,
        -0.45752933621406555,
        -0.04596840962767601,
        0.658467710018158
    ],
    "city_embedding": [
        -0.983634352684021,
        0.0106063736602664,
        0.6747356653213501,
        1.43538236618042,
        -0.614273190498352,
        1.2232292890548706,
        0.14563612639904022,
        2.863827705383301,
        2.349349021911621,
        3.518951892852783
    ],
    "degree_embedding": [
        -1.0942884683609009,
        3.680072784423828,
        0.8885844945907593,
        0.5826579332351685,
        0.03687247633934021,
        1.2447248697280884,
        -1.6899021863937378,
        -3.1763644218444824,
        1.7040141820907593,
        -2.1442885398864746
    ]
}