{
    "id": 3923,
    "range": [
        121.176804,
        31.052716,
        121.186804,
        31.042716
    ],
    "image_path": "CitySatellite\\Shanghai\\3923.jpg",
    "poi": [
        [
            2901,
            1,
            0
        ]
    ],
    "places": [],
    "transport": [
        [
            5621,
            4,
            1
        ]
    ],
    "traffic": [
        [
            5201,
            3,
            3
        ]
    ],
    "buildings": [
        7,
        9184.352499999999
    ],
    "landuse": [
        [
            7203,
            13,
            1,
            7.26225325
        ],
        [
            7202,
            2,
            0,
            0.198403
        ]
    ],
    "road_inner": [
        [
            5115,
            3,
            3,
            1706.9070000000002
        ],
        [
            5122,
            2,
            4,
            1697.3895
        ],
        [
            5113,
            6,
            2,
            4927.835166666668
        ],
        [
            5114,
            1,
            2,
            939.4590000000001
        ],
        [
            5141,
            1,
            5,
            1322.00725
        ]
    ],
    "road_connect": {
        "3802": {
            "2": 1
        },
        "3803": {
            "2": 4
        },
        "3800": {
            "2": 1
        },
        "3801": {
            "2": 1
        },
        "3799": {
            "2": 1
        },
        "3804": {
            "2": 1
        },
        "3922": {
            "2": 1,
            "5": 1,
            "4": 3
        },
        "4042": {
            "5": 1
        },
        "4043": {
            "5": 4,
            "2": 2
        },
        "3924": {
            "3": 1,
            "4": 1,
            "2": 3
        },
        "3925": {
            "2": 1
        }
    },
    "population": [
        8910.580619812012
    ],
    "transport_embedding": [
        -1.646101474761963,
        -0.5371153354644775,
        1.392444372177124,
        1.2679643630981445,
        -1.860100507736206,
        -0.07576530426740646,
        -0.18476012349128723,
        0.46464020013809204,
        -0.1474151611328125,
        -0.030032487586140633
    ],
    "roadnet_embedding": [
        -1.7454546689987183,
        -1.253050684928894,
        0.3592386543750763,
        2.040515422821045,
        -0.11260637640953064,
        -0.5154511332511902,
        1.462741494178772,
        0.12478898465633392,
        -0.13530220091342926,
        -0.4408080279827118
    ],
    "function_embedding": [
        -1.7031773328781128,
        0.0757758617401123,
        -1.8015801906585693,
        0.8822991847991943,
        0.8870357871055603,
        -0.272068589925766,
        -0.7119436860084534,
        -0.9954746961593628,
        -0.7757439613342285,
        2.5830273628234863
    ],
    "city_embedding": [
        -1.010807752609253,
        0.003024589503183961,
        -0.4417928159236908,
        0.5534824132919312,
        -0.6935960054397583,
        0.44931724667549133,
        1.4043489694595337,
        3.8832433223724365,
        2.2356231212615967,
        1.9261924028396606
    ],
    "degree_embedding": [
        -0.9839580059051514,
        -0.93036288022995,
        0.7199040651321411,
        -1.0253044366836548,
        -1.1611742973327637,
        0.43365976214408875,
        -0.056340333074331284,
        -1.5803014039993286,
        -2.757038116455078,
        1.2896056175231934
    ]
}