{
    "id": 4644,
    "range": [
        121.236804,
        31.042716,
        121.246804,
        31.032716
    ],
    "image_path": "CitySatellite\\Shanghai\\4644.jpg",
    "poi": [
        [
            2007,
            1,
            2
        ],
        [
            2510,
            1,
            6
        ],
        [
            2601,
            2,
            0
        ],
        [
            2561,
            1,
            6
        ],
        [
            2501,
            3,
            6
        ],
        [
            2012,
            1,
            2
        ],
        [
            2203,
            1,
            3
        ],
        [
            2302,
            1,
            4
        ],
        [
            2301,
            2,
            4
        ],
        [
            2111,
            1,
            0
        ],
        [
            2904,
            1,
            0
        ]
    ],
    "places": [
        [
            1010,
            1,
            5
        ]
    ],
    "transport": [],
    "traffic": [],
    "buildings": [
        251,
        146547.69099999964
    ],
    "landuse": [
        [
            7203,
            9,
            1,
            2.2080493333333333
        ],
        [
            7204,
            3,
            3,
            0.453078
        ],
        [
            7202,
            1,
            0,
            0.02638
        ]
    ],
    "road_inner": [
        [
            5115,
            4,
            3,
            3005.6710000000003
        ],
        [
            5122,
            6,
            4,
            520.917
        ],
        [
            5114,
            1,
            2,
            1720.1034999999997
        ],
        [
            5121,
            3,
            4,
            545.085
        ],
        [
            5141,
            16,
            5,
            1286.6549999999997
        ],
        [
            5153,
            5,
            5,
            248.58100000000002
        ]
    ],
    "road_connect": {
        "4643": {
            "2": 1,
            "3": 2
        },
        "4524": {
            "2": 1,
            "5": 1
        },
        "4764": {
            "3": 2,
            "2": 1
        },
        "4645": {
            "4": 2,
            "2": 1,
            "3": 2
        }
    },
    "population": [
        14023.8009262085
    ],
    "transport_embedding": [
        -0.25026142597198486,
        -0.6252150535583496,
        0.6704000234603882,
        -0.7770528793334961,
        0.4655011296272278,
        -0.7459458708763123,
        -0.33220890164375305,
        1.7197753190994263,
        -0.9918307662010193,
        -0.39577046036720276
    ],
    "roadnet_embedding": [
        0.7867084741592407,
        -1.000657558441162,
        0.4001100957393646,
        0.786645233631134,
        0.6544922590255737,
        0.6899074912071228,
        0.17621134221553802,
        -0.34647220373153687,
        -1.2456144094467163,
        1.7274342775344849
    ],
    "function_embedding": [
        -1.7216227054595947,
        0.09764325618743896,
        -2.1436309814453125,
        2.1487598419189453,
        0.7913045883178711,
        0.1700744926929474,
        -0.5495063066482544,
        -0.31037405133247375,
        -0.8122968077659607,
        -0.417022168636322
    ],
    "city_embedding": [
        -1.002731442451477,
        2.374631404876709,
        0.6224669814109802,
        4.209492206573486,
        4.819482803344727,
        -2.4982833862304688,
        -3.9820258617401123,
        4.204997539520264,
        4.145132064819336,
        3.2954607009887695
    ],
    "degree_embedding": [
        -0.988796591758728,
        -0.35975539684295654,
        -0.13227365911006927,
        -0.6606571674346924,
        0.822200357913971,
        0.22196727991104126,
        0.6175019145011902,
        -0.6003981232643127,
        0.510435938835144,
        -2.115158796310425
    ]
}