{
    "id": 5259,
    "range": [
        121.286804,
        30.892716,
        121.296804,
        30.882716
    ],
    "image_path": "CitySatellite\\Shanghai\\5259.jpg",
    "poi": [],
    "places": [],
    "transport": [
        [
            5621,
            2,
            1
        ]
    ],
    "traffic": [],
    "buildings": [],
    "landuse": [
        [
            7202,
            1,
            0,
            0.159962
        ]
    ],
    "road_inner": [
        [
            5122,
            1,
            4,
            1192.2146666666667
        ],
        [
            5123,
            1,
            5,
            5.537
        ],
        [
            5141,
            1,
            5,
            1397.6444000000001
        ],
        [
            5142,
            23,
            5,
            6390.437166666667
        ],
        [
            5121,
            1.0,
            4,
            586.4263333333333
        ],
        [
            5113,
            1.0,
            2,
            1193.2132
        ]
    ],
    "road_connect": {
        "5258": {
            "4": 1
        },
        "5257": {
            "4": 1
        },
        "5379": {
            "5": 4,
            "2": 2
        },
        "5018": {
            "5": 2,
            "2": 2
        },
        "5019": {
            "5": 2,
            "2": 2
        },
        "5139": {
            "5": 9,
            "2": 2
        },
        "5260": {
            "4": 1,
            "5": 3
        },
        "5380": {
            "4": 1
        },
        "5138": {
            "5": 1
        }
    },
    "population": [
        865.9686212539673
    ],
    "transport_embedding": [
        0.19432394206523895,
        -1.8408876657485962,
        -0.5668097138404846,
        0.009487292729318142,
        0.7743800282478333,
        0.9729499220848083,
        1.093031406402588,
        -1.6129324436187744,
        -1.2431057691574097,
        0.26712995767593384
    ],
    "roadnet_embedding": [
        1.1899495124816895,
        -0.9710743427276611,
        -1.5206732749938965,
        0.6657024621963501,
        0.5374969840049744,
        1.800309419631958,
        0.22545874118804932,
        2.29350209236145,
        0.5983068346977234,
        -0.5013428926467896
    ],
    "function_embedding": [
        -0.5477912425994873,
        -0.36813798546791077,
        -0.07924365997314453,
        0.03946704417467117,
        -1.3994299173355103,
        -0.012831350788474083,
        -0.15740099549293518,
        0.024304956197738647,
        0.04368234798312187,
        0.1281408965587616
    ],
    "city_embedding": [
        -0.9864915609359741,
        -0.0029392738360911608,
        0.5542798042297363,
        1.2594258785247803,
        -0.6088707447052002,
        1.1725212335586548,
        0.29880833625793457,
        2.904844045639038,
        2.333425283432007,
        3.3143701553344727
    ],
    "degree_embedding": [
        -0.9775756001472473,
        -1.2272124290466309,
        2.5312564373016357,
        0.4428035318851471,
        -1.9242061376571655,
        0.26813459396362305,
        -0.4544483423233032,
        -1.3576465845108032,
        1.2775572538375854,
        0.6383984684944153
    ]
}