{
    "id": 5473,
    "range": [
        121.306804,
        31.152716,
        121.316804,
        31.142716
    ],
    "image_path": "CitySatellite\\Shanghai\\5473.jpg",
    "poi": [
        [
            2601,
            6,
            0
        ],
        [
            2110,
            1,
            0
        ],
        [
            2303,
            2,
            4
        ],
        [
            2302,
            2,
            4
        ],
        [
            2501,
            1,
            6
        ]
    ],
    "places": [],
    "transport": [
        [
            5621,
            11,
            1
        ]
    ],
    "traffic": [],
    "buildings": [
        4,
        12633.017999999998
    ],
    "landuse": [
        [
            7203,
            8,
            1,
            5.013000666666667
        ],
        [
            7202,
            2,
            0,
            0.3701565
        ],
        [
            7209,
            1,
            2,
            0.5733185
        ],
        [
            7212,
            1,
            0,
            0.248865
        ]
    ],
    "road_inner": [
        [
            5115,
            12,
            3,
            4546.160666666667
        ],
        [
            5153,
            4,
            5,
            855.4853333333333
        ],
        [
            5122,
            20,
            4,
            3202.1904999999997
        ],
        [
            5121,
            3,
            4,
            920.7655
        ],
        [
            5124,
            1,
            5,
            148.696
        ],
        [
            5141,
            5,
            5,
            452.27
        ]
    ],
    "road_connect": {
        "5474": {
            "3": 5,
            "4": 2
        },
        "5353": {
            "3": 3,
            "4": 1
        },
        "5354": {
            "3": 1
        },
        "5472": {
            "3": 3,
            "5": 1,
            "4": 2
        },
        "5592": {
            "3": 1,
            "4": 1
        },
        "5593": {
            "5": 2,
            "4": 2,
            "3": 1
        }
    },
    "population": [
        14241.07888031006
    ],
    "transport_embedding": [
        -2.099613666534424,
        -0.022914273664355278,
        -1.2285051345825195,
        0.014611959457397461,
        -0.09005525708198547,
        0.12662506103515625,
        -0.49787890911102295,
        0.6553215980529785,
        0.3987617492675781,
        1.5782796144485474
    ],
    "roadnet_embedding": [
        1.018194556236267,
        -0.9868575930595398,
        1.1588250398635864,
        0.08599391579627991,
        0.41964977979660034,
        1.672227144241333,
        -1.066226840019226,
        -0.4571981430053711,
        -0.8483465909957886,
        3.1504909992218018
    ],
    "function_embedding": [
        -1.7262940406799316,
        0.10319387912750244,
        -2.2509539127349854,
        2.1767780780792236,
        0.7974390983581543,
        0.22120220959186554,
        -0.5664898157119751,
        -0.18260613083839417,
        -0.846846878528595,
        -0.6768432855606079
    ],
    "city_embedding": [
        -1.026453971862793,
        0.04970459267497063,
        -1.0681943893432617,
        0.11103006452322006,
        -0.5134042501449585,
        0.1666698157787323,
        2.098414897918701,
        3.256072521209717,
        3.0096631050109863,
        2.421302318572998
    ],
    "degree_embedding": [
        -1.0148218870162964,
        0.5297523736953735,
        0.19648730754852295,
        -2.022613763809204,
        0.5633595585823059,
        -1.6662769317626953,
        -0.23459239304065704,
        0.10483153909444809,
        1.3531689643859863,
        -0.47189709544181824
    ]
}