{
    "id": 5757,
    "range": [
        121.326804,
        30.712716,
        121.336804,
        30.702716
    ],
    "image_path": "CitySatellite\\Shanghai\\5757.jpg",
    "poi": [],
    "places": [],
    "transport": [],
    "traffic": [],
    "buildings": [],
    "landuse": [
        [
            7204,
            1,
            3,
            5.371056235294118
        ],
        [
            7203,
            4,
            1,
            1.08992675
        ],
        [
            7201,
            1,
            4,
            0.542414
        ],
        [
            7209,
            1,
            2,
            0.154658
        ]
    ],
    "road_inner": [
        [
            5115,
            4,
            3,
            4225.156333333333
        ],
        [
            5141,
            2,
            5,
            2680.9480714285714
        ],
        [
            5153,
            25,
            5,
            3526.0089999999996
        ]
    ],
    "road_connect": {
        "5278": {
            "5": 1
        },
        "5398": {
            "5": 1
        },
        "5518": {
            "5": 1
        },
        "5758": {
            "5": 5,
            "3": 1
        },
        "5638": {
            "5": 1
        },
        "5158": {
            "5": 1
        },
        "5517": {
            "3": 2
        },
        "5637": {
            "3": 3
        },
        "5756": {
            "3": 4
        },
        "5878": {
            "5": 1
        },
        "5877": {
            "5": 2,
            "3": 2
        },
        "5876": {
            "3": 1,
            "5": 1
        },
        "5996": {
            "5": 1
        }
    },
    "population": [
        4905.642274856567
    ],
    "transport_embedding": [
        -0.21834683418273926,
        -0.6942098140716553,
        0.607157289981842,
        -0.6951617002487183,
        0.7872452735900879,
        0.38193535804748535,
        -0.3764681816101074,
        1.084904432296753,
        -0.9608145952224731,
        -0.3908753991127014
    ],
    "roadnet_embedding": [
        1.543341040611267,
        -0.9370549321174622,
        -1.3233393430709839,
        0.6397444605827332,
        0.6450424194335938,
        2.061262607574463,
        0.05547603592276573,
        1.541220784187317,
        0.10602680593729019,
        -0.18025991320610046
    ],
    "function_embedding": [
        -1.5647697448730469,
        -0.08867479860782623,
        1.9844212532043457,
        0.42735570669174194,
        0.6216906905174255,
        2.5471808910369873,
        -0.3027590215206146,
        -0.4542194604873657,
        -0.05199854075908661,
        0.6440345048904419
    ],
    "city_embedding": [
        -0.9989802837371826,
        -0.020296579226851463,
        0.03795979544520378,
        0.707648754119873,
        -0.6537235379219055,
        0.8055880069732666,
        0.9035165905952454,
        3.4129626750946045,
        2.1553611755371094,
        2.360630989074707
    ],
    "degree_embedding": [
        -1.0029488801956177,
        -0.036446597427129745,
        1.5332342386245728,
        -1.5634056329727173,
        0.035553984344005585,
        -0.23714934289455414,
        0.25419124960899353,
        -0.5923625230789185,
        2.475672721862793,
        0.4964408278465271
    ]
}