{
    "id": 5979,
    "range": [
        121.346804,
        30.892716,
        121.356804,
        30.882716
    ],
    "image_path": "CitySatellite\\Shanghai\\5979.jpg",
    "poi": [],
    "places": [],
    "transport": [
        [
            5621,
            5,
            1
        ]
    ],
    "traffic": [],
    "buildings": [],
    "landuse": [
        [
            7204,
            8,
            3,
            4.24342375
        ]
    ],
    "road_inner": [
        [
            5122,
            1,
            4,
            1204.538
        ],
        [
            5115,
            2,
            3,
            2064.658
        ],
        [
            5114,
            1.0,
            2,
            356.80225
        ],
        [
            5142,
            1.0,
            5,
            448.1046666666667
        ],
        [
            5111,
            1.0,
            1,
            1252.8435
        ]
    ],
    "road_connect": {
        "5739": {
            "2": 1
        },
        "5859": {
            "2": 1,
            "3": 2
        },
        "5978": {
            "2": 1,
            "3": 1,
            "4": 1,
            "5": 1
        },
        "5980": {
            "3": 2,
            "1": 2,
            "4": 1
        },
        "6099": {
            "5": 2,
            "1": 2
        }
    },
    "population": [
        2979.656614303589
    ],
    "transport_embedding": [
        -0.7112054824829102,
        -1.7163386344909668,
        -1.5373190641403198,
        0.6110446453094482,
        -2.2136623859405518,
        -0.6634926795959473,
        -2.2146811485290527,
        1.7529505491256714,
        1.206634521484375,
        -0.4971925914287567
    ],
    "roadnet_embedding": [
        0.7121791839599609,
        -0.966934084892273,
        -0.1415427178144455,
        0.34497007727622986,
        0.9647571444511414,
        -0.6628737449645996,
        -0.641636848449707,
        -0.6223505735397339,
        0.4119606912136078,
        1.2799961566925049
    ],
    "function_embedding": [
        -1.4497654438018799,
        -0.2249351590871811,
        1.8748342990875244,
        0.00846045557409525,
        0.6542614698410034,
        2.451017379760742,
        -0.37323489785194397,
        -0.3757829964160919,
        -0.1137339174747467,
        0.2648586630821228
    ],
    "city_embedding": [
        -0.993105947971344,
        -0.016571473330259323,
        0.2796309292316437,
        0.9701710343360901,
        -0.6356980800628662,
        0.9757040143013,
        0.6206763982772827,
        3.1894094944000244,
        2.2258739471435547,
        2.7914137840270996
    ],
    "degree_embedding": [
        -0.995212733745575,
        -0.15784239768981934,
        0.3425845205783844,
        -0.6013492345809937,
        0.5835242867469788,
        0.2602839171886444,
        -0.12328089028596878,
        -0.82655268907547,
        0.4721710979938507,
        -2.415663957595825
    ]
}