{
    "id": 6828,
    "range": [
        121.416804,
        30.802716,
        121.426804,
        30.792716
    ],
    "image_path": "CitySatellite\\Shanghai\\6828.jpg",
    "poi": [],
    "places": [],
    "transport": [
        [
            5621,
            3,
            1
        ]
    ],
    "traffic": [
        [
            5204,
            1,
            1
        ]
    ],
    "buildings": [
        1,
        174.274
    ],
    "landuse": [],
    "road_inner": [
        [
            5115,
            7,
            3,
            2856.8723333333337
        ],
        [
            5112,
            3,
            1,
            1735.5358333333334
        ],
        [
            5114,
            2,
            2,
            943.5848333333334
        ],
        [
            5141,
            2,
            5,
            1594.0414999999998
        ],
        [
            5135,
            1,
            3,
            48.761
        ],
        [
            5122,
            1,
            4,
            313.41
        ],
        [
            5121,
            1.0,
            4,
            201.1235
        ]
    ],
    "road_connect": {
        "6710": {
            "2": 1
        },
        "6709": {
            "2": 1
        },
        "6829": {
            "2": 1,
            "3": 1
        },
        "6947": {
            "2": 1,
            "1": 2
        },
        "6948": {
            "2": 1
        },
        "6353": {
            "2": 1
        },
        "6472": {
            "2": 1
        },
        "6473": {
            "2": 1
        },
        "6471": {
            "2": 1
        },
        "6590": {
            "2": 1
        },
        "6591": {
            "2": 1
        },
        "6708": {
            "1": 2,
            "3": 2,
            "5": 2,
            "4": 1,
            "2": 1
        },
        "6827": {
            "3": 2,
            "1": 2,
            "5": 2
        },
        "6949": {
            "3": 1
        }
    },
    "population": [
        5951.651802062988
    ],
    "transport_embedding": [
        -0.1675177812576294,
        -2.06809139251709,
        -0.9761037230491638,
        0.6051145792007446,
        -0.4340755045413971,
        -0.33498841524124146,
        -0.42699331045150757,
        -0.379424124956131,
        -0.7690479159355164,
        -0.23027662932872772
    ],
    "roadnet_embedding": [
        0.9202837347984314,
        -0.9833021759986877,
        -0.266655832529068,
        0.7377963066101074,
        0.7691131234169006,
        0.39755764603614807,
        -0.4966813027858734,
        -0.8527573347091675,
        -0.06072647124528885,
        1.647581934928894
    ],
    "function_embedding": [
        -0.637988269329071,
        -0.29268860816955566,
        -0.06270430237054825,
        -0.05640212818980217,
        -1.3755441904067993,
        -0.05401355400681496,
        -0.08608879894018173,
        -0.11814236640930176,
        -0.1572805494070053,
        0.28080207109451294
    ],
    "city_embedding": [
        -1.002001166343689,
        -0.01564711332321167,
        -0.08455581218004227,
        0.5753187537193298,
        -0.6645189523696899,
        0.7034739255905151,
        1.0468144416809082,
        3.5393521785736084,
        2.105034351348877,
        2.1420981884002686
    ],
    "degree_embedding": [
        -1.0033131837844849,
        -0.064486064016819,
        0.9836089015007019,
        -1.2966523170471191,
        -0.3613116443157196,
        0.6178526878356934,
        -0.45207521319389343,
        -1.2293944358825684,
        -1.3848692178726196,
        -0.6369465589523315
    ]
}