{
    "id": 7161,
    "range": [
        121.446804,
        31.072716,
        121.456804,
        31.062716
    ],
    "image_path": "CitySatellite\\Shanghai\\7161.jpg",
    "poi": [],
    "places": [],
    "transport": [
        [
            5621,
            3,
            1
        ]
    ],
    "traffic": [
        [
            5201,
            3,
            3
        ]
    ],
    "buildings": [],
    "landuse": [
        [
            7204,
            3,
            3,
            4.522537375000001
        ],
        [
            7209,
            1,
            2,
            0.3226105
        ]
    ],
    "road_inner": [
        [
            5122,
            1,
            4,
            48.196
        ],
        [
            5114,
            1,
            2,
            625.05
        ],
        [
            5141,
            1,
            5,
            699.7103333333333
        ],
        [
            5115,
            1.0,
            3,
            766.544
        ],
        [
            5113,
            1.0,
            2,
            1011.29125
        ]
    ],
    "road_connect": {
        "7162": {
            "3": 1
        },
        "7160": {
            "2": 2,
            "3": 1,
            "5": 2
        },
        "7159": {
            "2": 2
        },
        "7281": {
            "2": 3
        },
        "7280": {
            "5": 1
        },
        "7040": {
            "5": 1
        },
        "7041": {
            "5": 1,
            "2": 1
        }
    },
    "population": [
        10236.58954620361
    ],
    "transport_embedding": [
        -1.7515721321105957,
        -0.33842733502388,
        2.778430700302124,
        1.6683158874511719,
        -1.7689208984375,
        0.09116940200328827,
        0.4944917559623718,
        -0.3051736354827881,
        -0.8215219974517822,
        -0.6042335033416748
    ],
    "roadnet_embedding": [
        0.033970192074775696,
        -1.002956509590149,
        0.2193594127893448,
        0.6702654957771301,
        0.5723730325698853,
        -0.94390469789505,
        0.8712193369865417,
        -0.01671176217496395,
        -0.8206027746200562,
        0.04537094011902809
    ],
    "function_embedding": [
        -1.4950611591339111,
        -0.17134690284729004,
        1.9236485958099365,
        0.1615826040506363,
        0.6424235701560974,
        2.489795684814453,
        -0.34989702701568604,
        -0.41137853264808655,
        -0.08849482983350754,
        0.40318289399147034
    ],
    "city_embedding": [
        -1.0145114660263062,
        0.005314853973686695,
        -0.5900865793228149,
        0.02560448832809925,
        -0.6084993481636047,
        0.3783811926841736,
        1.6121149063110352,
        3.587880849838257,
        2.2669930458068848,
        1.8265490531921387
    ],
    "degree_embedding": [
        -0.9782494902610779,
        -0.8921499252319336,
        0.6448295712471008,
        -0.35712915658950806,
        0.12471158057451248,
        0.7091783881187439,
        0.6666983962059021,
        -1.2640777826309204,
        -0.6960756778717041,
        -0.9910402297973633
    ]
}