{
    "id": 7303,
    "range": [
        121.456804,
        30.852716,
        121.466804,
        30.842716
    ],
    "image_path": "CitySatellite\\Shanghai\\7303.jpg",
    "poi": [],
    "places": [],
    "transport": [],
    "traffic": [],
    "buildings": [],
    "landuse": [
        [
            7204,
            2,
            3,
            0.7370350000000001
        ]
    ],
    "road_inner": [
        [
            5111,
            2,
            1,
            2549.4249999999997
        ],
        [
            5113,
            1,
            2,
            1360.3914166666666
        ],
        [
            5115,
            1.0,
            3,
            634.5932
        ]
    ],
    "road_connect": {
        "6944": {
            "3": 1
        },
        "7064": {
            "3": 1,
            "1": 2
        },
        "7063": {
            "3": 1
        },
        "7183": {
            "3": 1,
            "1": 2
        },
        "7184": {
            "1": 2
        },
        "7058": {
            "2": 1
        },
        "7059": {
            "2": 1
        },
        "7179": {
            "2": 1
        },
        "7182": {
            "2": 1
        },
        "7180": {
            "2": 1
        },
        "7181": {
            "2": 1
        },
        "7302": {
            "2": 1
        },
        "7423": {
            "1": 2
        },
        "7304": {
            "2": 1
        },
        "7424": {
            "2": 1
        }
    },
    "population": [
        1857.298466682434
    ],
    "transport_embedding": [
        -0.21039387583732605,
        -0.6500903964042664,
        0.6128485798835754,
        -0.7940853238105774,
        0.5442504286766052,
        -0.15509243309497833,
        -0.7871516346931458,
        1.063245415687561,
        -0.6019920706748962,
        -0.32840824127197266
    ],
    "roadnet_embedding": [
        0.12646232545375824,
        -1.0461338758468628,
        -1.032319188117981,
        0.7876223921775818,
        0.4932166635990143,
        -0.7306922078132629,
        -0.8069141507148743,
        -1.392940640449524,
        1.9404890537261963,
        0.3272474408149719
    ],
    "function_embedding": [
        -0.6233525276184082,
        -0.8808579444885254,
        0.42108258605003357,
        -1.6080540418624878,
        0.04174596816301346,
        1.0030004978179932,
        0.12629549205303192,
        0.6681676506996155,
        -0.3746238350868225,
        -0.9804162979125977
    ],
    "city_embedding": [
        -0.9896243214607239,
        -0.0101990457624197,
        0.4239528179168701,
        1.1220864057540894,
        -0.6240852475166321,
        1.07865309715271,
        0.4506572484970093,
        3.04740047454834,
        2.274292230606079,
        3.0558829307556152
    ],
    "degree_embedding": [
        -1.006929636001587,
        0.15309825539588928,
        0.8944723606109619,
        -1.2245227098464966,
        0.05494927242398262,
        0.6908125281333923,
        -0.45255306363105774,
        -1.2817338705062866,
        -0.9852897524833679,
        -1.7766063213348389
    ]
}