{
    "id": 7373,
    "range": [
        121.466804,
        31.352716,
        121.476804,
        31.342716
    ],
    "image_path": "CitySatellite\\Shanghai\\7373.jpg",
    "poi": [
        [
            2722,
            1,
            0
        ],
        [
            2301,
            1,
            4
        ]
    ],
    "places": [],
    "transport": [
        [
            5621,
            2,
            1
        ]
    ],
    "traffic": [],
    "buildings": [
        8,
        8351.023
    ],
    "landuse": [
        [
            7204,
            2,
            3,
            6.14314288888889
        ],
        [
            7202,
            1,
            0,
            1.463073
        ]
    ],
    "road_inner": [
        [
            5122,
            10,
            4,
            4634.3325
        ],
        [
            5141,
            7,
            5,
            3268.011
        ],
        [
            5124,
            1,
            5,
            148.041
        ],
        [
            5113,
            1.0,
            2,
            574.5936666666666
        ],
        [
            5153,
            1.0,
            5,
            187.5125
        ],
        [
            5114,
            1.0,
            2,
            1143.6245
        ],
        [
            5152,
            1.0,
            0,
            426.142
        ]
    ],
    "road_connect": {
        "7252": {
            "4": 1
        },
        "7253": {
            "4": 2,
            "2": 1,
            "5": 5
        },
        "7493": {
            "2": 2,
            "4": 2
        },
        "7372": {
            "4": 1,
            "5": 1
        },
        "7492": {
            "4": 1
        },
        "7374": {
            "2": 3,
            "5": 1,
            "4": 3,
            "0": 1
        },
        "7494": {
            "4": 1
        }
    },
    "population": [
        12262.26409912109
    ],
    "transport_embedding": [
        0.1608443409204483,
        -1.9358241558074951,
        -0.7695016860961914,
        0.09287046641111374,
        0.647030234336853,
        0.7409506440162659,
        1.161824345588684,
        -1.4300874471664429,
        -1.4632806777954102,
        0.25040483474731445
    ],
    "roadnet_embedding": [
        0.10975996404886246,
        -1.0747313499450684,
        0.23358705639839172,
        0.19961678981781006,
        0.10742062330245972,
        1.1472710371017456,
        -0.02311871014535427,
        0.4249199330806732,
        0.24554990231990814,
        -0.81108558177948
    ],
    "function_embedding": [
        -1.5749751329421997,
        -0.07659120857715607,
        1.9328874349594116,
        0.6840825080871582,
        0.6019188761711121,
        2.5241122245788574,
        -0.2629648745059967,
        -0.44399213790893555,
        -0.050127241760492325,
        0.8977511525154114
    ],
    "city_embedding": [
        -1.020185947418213,
        0.04007338732481003,
        -0.8137377500534058,
        0.14632727205753326,
        -0.5789003968238831,
        0.20465914905071259,
        1.8101180791854858,
        3.638869524002075,
        2.5292184352874756,
        2.0816872119903564
    ],
    "degree_embedding": [
        -0.9876529574394226,
        -0.6159299612045288,
        -0.43064433336257935,
        0.22544053196907043,
        -0.8617348670959473,
        -0.9564529061317444,
        -1.7804198265075684,
        -0.7664464116096497,
        -0.04586903378367424,
        0.33256056904792786
    ]
}