{
    "id": 7642,
    "range": [
        121.486804,
        31.062716,
        121.496804,
        31.052716
    ],
    "image_path": "CitySatellite\\Shanghai\\7642.jpg",
    "poi": [
        [
            2016,
            1,
            2
        ],
        [
            2421,
            1,
            5
        ]
    ],
    "places": [
        [
            1010,
            1,
            5
        ]
    ],
    "transport": [
        [
            5621,
            3,
            1
        ]
    ],
    "traffic": [],
    "buildings": [
        5,
        28871.142999999996
    ],
    "landuse": [
        [
            7206,
            1,
            0,
            0.2619665
        ],
        [
            7203,
            7,
            1,
            1.0122555
        ],
        [
            7201,
            1,
            4,
            2.9468644166666667
        ],
        [
            7229,
            3,
            5,
            0.128615
        ]
    ],
    "road_inner": [
        [
            5141,
            14,
            5,
            1572.8835
        ],
        [
            5122,
            8,
            4,
            2802.4626666666663
        ],
        [
            5152,
            11,
            0,
            2197.4295
        ],
        [
            5113,
            6,
            2,
            2217.975000000001
        ],
        [
            5154,
            4,
            5,
            1150.781
        ],
        [
            5153,
            16,
            5,
            2066.011
        ],
        [
            5115,
            1,
            3,
            575.4235
        ],
        [
            5111,
            1.0,
            1,
            1546.7775000000001
        ],
        [
            5121,
            1.0,
            4,
            407.172
        ]
    ],
    "road_connect": {
        "7762": {
            "1": 2,
            "2": 2,
            "4": 1,
            "5": 1,
            "3": 1
        },
        "7882": {
            "1": 2
        },
        "7522": {
            "1": 2,
            "4": 5,
            "2": 2,
            "3": 1,
            "5": 1
        },
        "8002": {
            "1": 1
        },
        "7761": {
            "4": 1
        },
        "7641": {
            "4": 1,
            "5": 1,
            "0": 1
        },
        "7523": {
            "4": 1
        },
        "7643": {
            "4": 3
        }
    },
    "population": [
        2920.553157806396
    ],
    "transport_embedding": [
        0.003086691489443183,
        -2.309556722640991,
        -1.4792746305465698,
        0.5445812940597534,
        -0.6669716238975525,
        -0.45082220435142517,
        -0.9091959595680237,
        0.013045688159763813,
        -0.40497827529907227,
        -0.23548725247383118
    ],
    "roadnet_embedding": [
        0.3824249505996704,
        -1.0486913919448853,
        -0.8978157639503479,
        0.6975120306015015,
        0.28960826992988586,
        1.2282930612564087,
        0.29497015476226807,
        1.2424542903900146,
        0.7679842114448547,
        -0.41734132170677185
    ],
    "function_embedding": [
        1.079193115234375,
        -3.2156753540039062,
        -1.2571418285369873,
        1.3150452375411987,
        0.435444712638855,
        0.8826666474342346,
        -0.2741453945636749,
        2.8011200428009033,
        -0.8073451519012451,
        5.4926981925964355
    ],
    "city_embedding": [
        -0.9768480062484741,
        1.6176198720932007,
        1.514058232307434,
        2.3220512866973877,
        5.605928897857666,
        -0.7973451614379883,
        -4.265939712524414,
        2.5632781982421875,
        8.332056999206543,
        3.2648959159851074
    ],
    "degree_embedding": [
        -1.0124616622924805,
        0.3460777699947357,
        -0.05163903161883354,
        -0.1356656402349472,
        -0.7523326277732849,
        -1.0283581018447876,
        -2.461817502975464,
        -0.8508687019348145,
        -0.1519668996334076,
        -0.6002340316772461
    ]
}