{
    "id": 7887,
    "range": [
        121.506804,
        31.012716,
        121.516804,
        31.002716
    ],
    "image_path": "CitySatellite\\Shanghai\\7887.jpg",
    "poi": [],
    "places": [],
    "transport": [
        [
            5621,
            2,
            1
        ]
    ],
    "traffic": [],
    "buildings": [],
    "landuse": [
        [
            7201,
            1,
            4,
            0.741731
        ]
    ],
    "road_inner": [
        [
            5121,
            1,
            4,
            1665.5875
        ],
        [
            5122,
            13,
            4,
            2926.926833333333
        ],
        [
            5141,
            2,
            5,
            952.9449999999999
        ],
        [
            5115,
            1.0,
            3,
            935.44
        ],
        [
            5154,
            1.0,
            5,
            530.3975
        ],
        [
            5113,
            1.0,
            2,
            851.492
        ]
    ],
    "road_connect": {
        "7768": {
            "4": 1
        },
        "7767": {
            "4": 3,
            "3": 1,
            "5": 2
        },
        "7648": {
            "4": 1
        },
        "7886": {
            "4": 3,
            "2": 2,
            "5": 1
        },
        "7888": {
            "4": 1,
            "2": 2
        },
        "8007": {
            "4": 2,
            "3": 1
        }
    },
    "population": [
        5178.652763366699
    ],
    "transport_embedding": [
        0.1689622551202774,
        -1.8500697612762451,
        -0.5774900913238525,
        0.034383609890937805,
        0.7661641836166382,
        0.8413103818893433,
        1.0465519428253174,
        -1.689640760421753,
        -1.3720606565475464,
        0.2469954937696457
    ],
    "roadnet_embedding": [
        -0.14903350174427032,
        -1.0988892316818237,
        1.115387201309204,
        -0.9361342191696167,
        -0.16726267337799072,
        0.9544995427131653,
        -0.4359121024608612,
        -0.028977621346712112,
        -0.02344287745654583,
        -0.10552646219730377
    ],
    "function_embedding": [
        0.23244880139827728,
        -1.6760871410369873,
        -0.6594288945198059,
        0.2045142650604248,
        -0.15654969215393066,
        0.6144136190414429,
        -0.543096125125885,
        2.1094250679016113,
        0.09560638666152954,
        2.5934879779815674
    ],
    "city_embedding": [
        -0.9997981190681458,
        -0.020052004605531693,
        0.004514830652624369,
        0.6707420945167542,
        -0.6560835242271423,
        0.7818440794944763,
        0.943168580532074,
        3.4422366619110107,
        2.1459546089172363,
        2.30248761177063
    ],
    "degree_embedding": [
        -0.9874293804168701,
        -0.5686596632003784,
        -0.8816804885864258,
        0.09579993039369583,
        -0.5573691129684448,
        -1.0800029039382935,
        -1.8886064291000366,
        -1.2549439668655396,
        0.23036503791809082,
        0.14148874580860138
    ]
}