{
    "id": 8000,
    "range": [
        121.516804,
        31.082716,
        121.526804,
        31.072716
    ],
    "image_path": "CitySatellite\\Shanghai\\8000.jpg",
    "poi": [
        [
            2301,
            1,
            4
        ]
    ],
    "places": [],
    "transport": [
        [
            5621,
            5,
            1
        ]
    ],
    "traffic": [
        [
            5201,
            2,
            3
        ]
    ],
    "buildings": [
        9,
        83900.7335
    ],
    "landuse": [
        [
            7203,
            1,
            1,
            0.3419865
        ],
        [
            7209,
            4,
            2,
            1.624099
        ],
        [
            7204,
            3,
            3,
            0.8593189999999999
        ]
    ],
    "road_inner": [
        [
            5114,
            2,
            2,
            854.3906666666667
        ],
        [
            5115,
            1,
            3,
            1809.8670000000002
        ],
        [
            5122,
            1,
            4,
            940.9943333333333
        ],
        [
            5153,
            1,
            5,
            418.77250000000004
        ],
        [
            5141,
            1.0,
            5,
            867.6475
        ],
        [
            5121,
            1.0,
            4,
            380.4275
        ]
    ],
    "road_connect": {
        "7880": {
            "3": 1,
            "4": 1
        },
        "8001": {
            "4": 1,
            "2": 1
        },
        "7879": {
            "2": 1
        },
        "7999": {
            "2": 1,
            "3": 1,
            "5": 3,
            "4": 1
        },
        "8120": {
            "3": 2,
            "4": 1
        },
        "8119": {
            "3": 1
        }
    },
    "population": [
        4061.366268157959
    ],
    "transport_embedding": [
        -1.5836055278778076,
        -0.6284422874450684,
        0.8582795262336731,
        1.1053849458694458,
        -1.7883883714675903,
        -0.13263867795467377,
        -0.45900294184684753,
        0.6581574082374573,
        0.07532501220703125,
        0.06685296446084976
    ],
    "roadnet_embedding": [
        0.8212458491325378,
        -0.9659754633903503,
        0.2440500557422638,
        -0.005989136639982462,
        0.7493242025375366,
        -0.07808780670166016,
        0.23935019969940186,
        -0.22927957773208618,
        -0.9968011975288391,
        0.5312861800193787
    ],
    "function_embedding": [
        -1.2445186376571655,
        -0.4239555597305298,
        -0.41794583201408386,
        0.5252051949501038,
        0.6558942794799805,
        -0.37497857213020325,
        0.31909340620040894,
        -0.9071069955825806,
        3.705105781555176,
        2.457029104232788
    ],
    "city_embedding": [
        -1.007455825805664,
        -0.18817949295043945,
        -0.3691413700580597,
        3.030033588409424,
        -0.7070433497428894,
        1.6512341499328613,
        0.7487123608589172,
        2.7109363079071045,
        3.467360734939575,
        2.524207830429077
    ],
    "degree_embedding": [
        -0.9848285913467407,
        -0.5336825847625732,
        -0.3197322487831116,
        -0.2996878921985626,
        0.5392426252365112,
        0.05686229467391968,
        0.04986624792218208,
        -0.8934550285339355,
        0.786048948764801,
        -1.7782025337219238
    ]
}