{
    "id": 9421,
    "range": [
        121.636804,
        31.272716,
        121.646804,
        31.262716
    ],
    "image_path": "CitySatellite\\Shanghai\\9421.jpg",
    "poi": [
        [
            2301,
            1,
            4
        ]
    ],
    "places": [],
    "transport": [
        [
            5621,
            4,
            1
        ]
    ],
    "traffic": [
        [
            5206,
            1,
            2
        ],
        [
            5204,
            4,
            1
        ]
    ],
    "buildings": [
        1,
        9937.6475
    ],
    "landuse": [
        [
            7201,
            2,
            4,
            0.39383975
        ],
        [
            7202,
            5,
            0,
            2.8638550000000005
        ],
        [
            7203,
            1,
            1,
            0.2710815
        ]
    ],
    "road_inner": [
        [
            5111,
            13,
            1,
            2290.0559999999996
        ],
        [
            5131,
            20,
            1,
            2236.5915
        ],
        [
            5153,
            2,
            5,
            91.99799999999999
        ],
        [
            5115,
            2,
            3,
            969.923
        ],
        [
            5121,
            4,
            4,
            1817.57325
        ],
        [
            5141,
            5,
            5,
            1668.855
        ],
        [
            5113,
            2,
            2,
            2250.834
        ],
        [
            5152,
            1.0,
            0,
            1558.8976666666665
        ],
        [
            5122,
            1.0,
            4,
            917.5358333333334
        ],
        [
            5154,
            1.0,
            5,
            91.415
        ]
    ],
    "road_connect": {
        "9181": {
            "0": 2
        },
        "9781": {
            "0": 2
        },
        "9301": {
            "0": 2,
            "2": 2,
            "3": 2,
            "4": 1,
            "5": 3
        },
        "9541": {
            "0": 2,
            "4": 2,
            "3": 1,
            "5": 1,
            "2": 2
        },
        "9661": {
            "0": 2
        },
        "9300": {
            "5": 1
        },
        "9420": {
            "5": 1,
            "3": 2,
            "4": 1,
            "1": 2
        },
        "9422": {
            "1": 4,
            "4": 3,
            "5": 1
        },
        "9542": {
            "4": 3
        }
    },
    "population": [
        6132.937881469727
    ],
    "transport_embedding": [
        -1.241909146308899,
        -0.9112858176231384,
        -0.29053640365600586,
        0.5811948180198669,
        -0.14729419350624084,
        -0.10594771057367325,
        0.11012624949216843,
        -0.3467336893081665,
        -0.5844196081161499,
        -1.3057656288146973
    ],
    "roadnet_embedding": [
        -0.7204869985580444,
        -1.154349446296692,
        -1.4136031866073608,
        0.9168872237205505,
        0.00692554097622633,
        0.13994188606739044,
        -1.2880134582519531,
        -1.410844326019287,
        0.8565431237220764,
        -0.322042316198349
    ],
    "function_embedding": [
        0.05882025137543678,
        -2.005566120147705,
        -0.9696475267410278,
        -1.0634291172027588,
        0.7482847571372986,
        1.1032160520553589,
        -0.9403558373451233,
        2.8367903232574463,
        2.040731430053711,
        -3.421077251434326
    ],
    "city_embedding": [
        -1.0035827159881592,
        -0.045711591839790344,
        -0.16019441187381744,
        0.9110080003738403,
        -0.7164503335952759,
        0.7561533451080322,
        1.0925498008728027,
        3.727468490600586,
        2.320927619934082,
        2.1450626850128174
    ],
    "degree_embedding": [
        -1.0223305225372314,
        0.6099470257759094,
        0.5087165832519531,
        0.1023455336689949,
        -1.691576361656189,
        0.2723694443702698,
        -3.6614060401916504,
        4.152581691741943,
        0.2422138899564743,
        -1.214388132095337
    ]
}